TA_using_LLMs/__init__.py
TA_using_LLMs/logic.py
TA_using_LLMs/main.py
ta_using_llms-0.0.4.dist-info/LICENSE
ta_using_llms-0.0.4.dist-info/METADATA
ta_using_llms-0.0.4.dist-info/WHEEL
ta_using_llms-0.0.4.dist-info/entry_points.txt
ta_using_llms-0.0.4.dist-info/top_level.txt
ta_using_llms-0.0.4.dist-info/RECORD
